epicenv/__init__.py
epicenv/_config.py
epicenv/_env.py
epicenv/_exceptions.py
epicenv/py.typed
epicenv/cli/__init__.py
epicenv/cli/create.py
epicenv/cli/diff.py
epicenv/cli/main.py
epicenv/cli/validate.py
epicenv/initializers/__init__.py
epicenv/initializers/_onepassword.py
epicenv/initializers/_passwords.py
epicenv/management/__init__.py
epicenv/management/commands/__init__.py
epicenv/management/commands/create_env_file.py
epicenv/management/commands/diff_env_file.py
epicenv-1.2.0.dist-info/METADATA
epicenv-1.2.0.dist-info/WHEEL
epicenv-1.2.0.dist-info/entry_points.txt
epicenv-1.2.0.dist-info/licenses/LICENSE
epicenv-1.2.0.dist-info/RECORD
